metabolitics3d/__init__.py
metabolitics3d/tests.py
metabolitics3d/analysis/__init__.py
metabolitics3d/analysis/analysis.py
metabolitics3d/analysis/tests.py
metabolitics3d/datasets/naming/cheBl-mapping.json
metabolitics3d/datasets/naming/hmdb-mapping.json
metabolitics3d/datasets/naming/kegg-mapping.json
metabolitics3d/datasets/naming/pubChem-mapping.json
metabolitics3d/datasets/naming/toy-mapping.json
metabolitics3d/datasets/network_models/recon3D.json
metabolitics3d/extensions/__init__.py
metabolitics3d/extensions/metabolite_extantions.py
metabolitics3d/extensions/model_extantions.py
metabolitics3d/extensions/tests.py
metabolitics3d/preprocessing/__init__.py
metabolitics3d/preprocessing/metabolitics_pipeline.py
metabolitics3d/preprocessing/metabolitics_transformer.py
metabolitics3d/preprocessing/pathway_reaction_enrichment.py
metabolitics3d/preprocessing/pathway_transformer.py
metabolitics3d/preprocessing/reaction_diff_transformer.py
metabolitics3d/preprocessing/tests.py
metabolitics3d/preprocessing/transport_pathway_elimination.py
metabolitics3d/utils/__init__.py
metabolitics3d/utils/io_utils.py
metabolitics3d/utils/tests.py
metabolitics3d-0.0.12.dist-info/LICENSE
metabolitics3d-0.0.12.dist-info/METADATA
metabolitics3d-0.0.12.dist-info/WHEEL
metabolitics3d-0.0.12.dist-info/top_level.txt
metabolitics3d-0.0.12.dist-info/RECORD
